flask_orm/__init__.py
flask_orm/base_model.py
flask_orm/base_query.py
flask_orm/engine.py
flask_orm/orm_settings.py
flask_orm-0.0.2.dist-info/WHEEL
flask_orm-0.0.2.dist-info/METADATA
flask_orm-0.0.2.dist-info/RECORD
