Metadata-Version: 2.1
Name: flask-orm
Version: 0.0.2
Summary: an easy way to use sqlalchemy in your flask app
Author: kyle roux
Author-email: jstacoder@gmail.com
Classifier: Programming Language :: Python :: 2
Classifier: Programming Language :: Python :: 2.7
Classifier: Programming Language :: Python :: 3
Classifier: Programming Language :: Python :: 3.4
Classifier: Programming Language :: Python :: 3.5
Classifier: Programming Language :: Python :: 3.6
Classifier: Programming Language :: Python :: 3.7
Requires-Dist: flask (>=1.0,<2.0)
Requires-Dist: pytest (>=4.4,<5.0)
Requires-Dist: sqlalchemy (>=1.3,<2.0)
Requires-Dist: sqlalchemy-stubs (>=0.1.0,<0.2.0)
Requires-Dist: typing-extensions (>=3.7,<4.0)
